qcfractal/__init__.py
qcfractal/alembic.ini
qcfractal/config.py
qcfractal/job_runner.py
qcfractal/old_config.py
qcfractal/port_util.py
qcfractal/postgres_harness.py
qcfractal/process_targets.py
qcfractal/qcfractal_server_cli.py
qcfractal/snowflake.py
qcfractal/test_config.py
qcfractal/test_db_connection.py
qcfractal/test_periodics.py
qcfractal/test_server_cli.py
qcfractal/test_snowflake.py
qcfractal/testing_helpers.py
qcfractal/alembic/env.py
qcfractal/alembic/script.py.mako
qcfractal/alembic/versions/2019-07-02-d28e52d86633_add_username_to_manager.py
qcfractal/alembic/versions/2019-07-09-6adeb5d3032e_service_ordering.py
qcfractal/alembic/versions/2019-07-23-26cfd7b0439e_add_access_logs_table.py
qcfractal/alembic/versions/2019-07-26-4bb79efa9855_add_queue_manager_id_to_base_results.py
qcfractal/alembic/versions/2019-08-10-963822c28879_molecule_msgpack_1.py
qcfractal/alembic/versions/2019-08-11-05ceea11b78a_base_records_msgpack_2.py
qcfractal/alembic/versions/2019-08-11-1134312ad4a3_results_msgpack_2.py
qcfractal/alembic/versions/2019-08-11-84c94a48e491_results_msgpack_1.py
qcfractal/alembic/versions/2019-08-11-8b0cd9accaf2_base_records_msgpack_1.py
qcfractal/alembic/versions/2019-08-11-d56ac42b9a43_molecule_msgpack_2.py
qcfractal/alembic/versions/2019-08-12-da7c6f141bcb_extras_msgpack_1.py
qcfractal/alembic/versions/2019-08-12-e32b61e2516f_extras_msgpack_2.py
qcfractal/alembic/versions/2019-08-19-129ff3ce9247_add_collection_tables_dataset_reaction_.py
qcfractal/alembic/versions/2019-09-19-cc54842bb6ba_updates_dataset_pk.py
qcfractal/alembic/versions/2019-09-30-c194a8ef6acf_protocols.py
qcfractal/alembic/versions/2019-10-08-a2f76bb7be65_updates_collections_table_with_owner_.py
qcfractal/alembic/versions/2019-10-17-1bd2f7711e68_wavefunction_table.py
qcfractal/alembic/versions/2019-10-29-d5d88ac1d291_instrumentation.py
qcfractal/alembic/versions/2019-11-01-159ba85908fd_add_contributed_values_table.py
qcfractal/alembic/versions/2019-11-06-4b27843a188a_v12_final.py
qcfractal-0.63.dist-info/licenses/LICENSE
qcfractal-0.63.dist-info/METADATA
qcfractal-0.63.dist-info/WHEEL
qcfractal-0.63.dist-info/entry_points.txt
qcfractal-0.63.dist-info/top_level.txt
qcfractal-0.63.dist-info/RECORD
