Metadata-Version: 2.4
Name: qcfractal
Version: 0.63
Summary: A distributed compute and database platform for quantum chemistry.
Author-email: Benjamin Pritchard <qcarchive@molssi.org>
License-Expression: BSD-3-Clause
Project-URL: Homepage, https://github.com/MolSSI/QCFractal
Project-URL: Bug Tracker, https://github.com/MolSSI/QCFractal/issues
Classifier: Programming Language :: Python :: 3
Classifier: Development Status :: 4 - Beta
Classifier: Intended Audience :: Science/Research
Classifier: Operating System :: POSIX :: Linux
Classifier: Operating System :: MacOS
Requires-Python: >=3.10
License-File: LICENSE
Requires-Dist: flask
Requires-Dist: flask-jwt-extended
Requires-Dist: flask-cors
Requires-Dist: waitress
Requires-Dist: bcrypt
Requires-Dist: sqlalchemy>=2.0
Requires-Dist: alembic
Requires-Dist: psycopg2
Requires-Dist: qcportal
Provides-Extra: services
Requires-Dist: torsiondrive; extra == "services"
Requires-Dist: qcmanybody; extra == "services"
Requires-Dist: geometric; extra == "services"
Provides-Extra: geoip
Requires-Dist: geoip2; extra == "geoip"
Provides-Extra: snowflake
Requires-Dist: qcfractalcompute; extra == "snowflake"
Provides-Extra: s3
Requires-Dist: boto3; extra == "s3"
Dynamic: license-file
